{
  "students": [
    {
      "id": 1,
      "name": "赵阳阳01",
      "grade": "初一",
      "password_hash": "7183ebd3b5c43c8b73f91ff8a94060f8$84ae782b16167292c7c61ff38b68b0be20b7c3591c10713a1bb4122dbbb57119",
      "phone": "17866812222",
      "avatar_url": null,
      "status": "active",
      "last_login_at": "2026-03-29T19:37:15.158002",
      "created_at": "2026-03-16T16:43:29.844085",
      "updated_at": "2026-03-29T19:37:15.158019"
    },
    {
      "id": 2,
      "name": "zhaoyang",
      "grade": "初一",
      "password_hash": "b7bc4f9697a3ed1164fde9ff6b9bba32$ade4d3c3a4894f81256a3a4d0949775a564434c95b6f8916c31830b7da800be0",
      "phone": "17866813333",
      "avatar_url": null,
      "status": "active",
      "last_login_at": "2026-03-17T15:29:07.030547",
      "created_at": "2026-03-17T15:28:42.970394",
      "updated_at": "2026-03-17T15:29:07.030557"
    },
    {
      "id": 3,
      "name": "赵阳阳",
      "grade": "初一",
      "password_hash": "3b99dd33118f33db9464149eccbef38c$3a9c9a56598c455e8fd86f4561f1cb32780bf9953febb91e69f19e103fdb5310",
      "phone": "17866819281",
      "avatar_url": null,
      "status": "active",
      "last_login_at": "2026-03-30T16:12:20.780282",
      "created_at": "2026-03-29T17:45:17.477196",
      "updated_at": "2026-03-30T16:12:20.780298"
    }
  ],
  "next_id": 3,
  "profiles": [
    {
      "id": 1,
      "student_id": 1,
      "course_id": "MATH_JUNIOR_01",
      "current_kp_id": "K11",
      "completed_kp_ids": [
        "K9",
        "K10",
        "K11"
      ],
      "mastered_kp_ids": [
        "K1",
        "K3",
        "K4",
        "K5",
        "K2",
        "K6",
        "K7",
        "K8"
      ],
      "skipped_kp_ids": [],
      "mastery_rate": 0.25,
      "total_time": 0,
      "session_count": 0,
      "last_session_at": null,
      "created_at": "2026-03-16T21:49:11.136918",
      "updated_at": "2026-04-03T22:27:01.626309"
    },
    {
      "id": 2,
      "student_id": 2,
      "course_id": "MATH_JUNIOR_01",
      "current_kp_id": "K17",
      "completed_kp_ids": [
        "K17"
      ],
      "mastered_kp_ids": [
        "K1",
        "K3",
        "K4",
        "K5",
        "K2",
        "K6",
        "K7",
        "K8",
        "K9",
        "K10",
        "K11",
        "K12",
        "K13",
        "K14",
        "K15",
        "K16"
      ],
      "skipped_kp_ids": [],
      "mastery_rate": 0.5,
      "total_time": 0,
      "session_count": 0,
      "last_session_at": null,
      "created_at": "2026-03-17T15:29:07.456618",
      "updated_at": "2026-03-17T20:11:20.937297"
    },
    {
      "id": 3,
      "student_id": 3,
      "course_id": "linear-function",
      "current_kp_id": null,
      "completed_kp_ids": [],
      "mastered_kp_ids": [],
      "skipped_kp_ids": [],
      "mastery_rate": 0.0,
      "total_time": 0,
      "session_count": 0,
      "last_session_at": null,
      "created_at": "2026-03-29T20:48:37.668184",
      "updated_at": "2026-03-29T20:48:37.668197"
    },
    {
      "id": 4,
      "student_id": 3,
      "course_id": "MATH_JUNIOR_01",
      "current_kp_id": null,
      "completed_kp_ids": [],
      "mastered_kp_ids": [],
      "skipped_kp_ids": [],
      "mastery_rate": 0.0,
      "total_time": 0,
      "session_count": 0,
      "last_session_at": null,
      "created_at": "2026-03-29T20:49:55.775071",
      "updated_at": "2026-03-29T20:49:55.775079"
    }
  ],
  "next_profile_id": 4,
  "updated_at": "2026-04-03T22:27:01.627903"
}